ai_tictactoe/__init__.py
ai_tictactoe/tictactoe.py
ai_tictactoe-0.1.5.dist-info/METADATA
ai_tictactoe-0.1.5.dist-info/WHEEL
ai_tictactoe-0.1.5.dist-info/top_level.txt
ai_tictactoe-0.1.5.dist-info/RECORD
