Metadata-Version: 2.1
Name: ai_tictactoe
Version: 0.1.5
Summary: A Tic-Tac-Toe game with AI opponent
Home-page: https://github.com/bzm10/ai_tictactoe
Author: Benjamin M
Author-email: bzmarkovits@yahoo.com
Requires-Python: >=3.6
